cvg_sdk/__init__.py
cvg_sdk/api_client.py
cvg_sdk/configuration.py
cvg_sdk/exceptions.py
cvg_sdk/model_utils.py
cvg_sdk/rest.py
cvg_sdk/api/__init__.py
cvg_sdk/api/assist_api.py
cvg_sdk/api/call_api.py
cvg_sdk/api/dialog_api.py
cvg_sdk/api/health_api.py
cvg_sdk/api/recording_api.py
cvg_sdk/apis/__init__.py
cvg_sdk/model/__init__.py
cvg_sdk/model/accept_assist_parameters.py
cvg_sdk/model/aggregated_latencies.py
cvg_sdk/model/answer.py
cvg_sdk/model/answer_all_of.py
cvg_sdk/model/answer_type.py
cvg_sdk/model/assist_recording_start_parameters.py
cvg_sdk/model/assist_recording_start_parameters_all_of.py
cvg_sdk/model/assist_recording_stop_parameters.py
cvg_sdk/model/audio.py
cvg_sdk/model/audio_all_of.py
cvg_sdk/model/audio_playback_failed.py
cvg_sdk/model/audio_playback_failed_all_of.py
cvg_sdk/model/barge_in_options.py
cvg_sdk/model/barge_in_options_one_of.py
cvg_sdk/model/bridge.py
cvg_sdk/model/bridge_parameters.py
cvg_sdk/model/bridge_parameters_all_of.py
cvg_sdk/model/call_parameters.py
cvg_sdk/model/call_transfer_parameters.py
cvg_sdk/model/call_transfer_parameters_all_of.py
cvg_sdk/model/call_transfer_whispering.py
cvg_sdk/model/confidence.py
cvg_sdk/model/custom.py
cvg_sdk/model/custom_all_of.py
cvg_sdk/model/custom_sip_headers.py
cvg_sdk/model/data_parameters.py
cvg_sdk/model/data_parameters_all_of.py
cvg_sdk/model/dial_parameters.py
cvg_sdk/model/dial_parameters_all_of.py
cvg_sdk/model/dialog.py
cvg_sdk/model/dialog_data_parameters.py
cvg_sdk/model/dialog_phase.py
cvg_sdk/model/drop_parameters.py
cvg_sdk/model/dtmf.py
cvg_sdk/model/dtmf_all_of.py
cvg_sdk/model/end.py
cvg_sdk/model/end_all_of.py
cvg_sdk/model/endpoint_call.py
cvg_sdk/model/endpoint_call_all_of.py
cvg_sdk/model/endpoint_call_failed.py
cvg_sdk/model/endpoint_call_failed_all_of.py
cvg_sdk/model/entry.py
cvg_sdk/model/entry_type.py
cvg_sdk/model/external_call_id.py
cvg_sdk/model/forward.py
cvg_sdk/model/forward_all_of.py
cvg_sdk/model/forward_parameters.py
cvg_python_sdk-0.5.1.dist-info/METADATA
cvg_python_sdk-0.5.1.dist-info/WHEEL
cvg_python_sdk-0.5.1.dist-info/top_level.txt
cvg_python_sdk-0.5.1.dist-info/RECORD
